{
  "tag": "temporal_B_input_dep_eta0.04_t50000_seed0",
  "condition": "B",
  "seed": 0,
  "noise_type": "input_dep",
  "eta": 0.04,
  "transition_epoch": 50000,
  "p": 97,
  "n_train": 5000,
  "hidden": 256,
  "batch_size": 512,
  "epochs_ran": 52000,
  "epochs_planned": 200000,
  "eval_every": 2000,
  "lr": 0.001,
  "weight_decay": 0.02,
  "grok_threshold": 0.95,
  "grok_consecutive": 5,
  "num_corrupted": 200,
  "time_to_grok": 38000,
  "time_to_0.80": 22000,
  "time_to_0.90": 30000,
  "final_test_acc": 0.7738335636093102,
  "final_train_acc": 0.9828,
  "gap_area": 5.887434626421513,
  "phase1_final_test_acc": 0.970241258369646,
  "phase1_grokked": true,
  "wall_time_sec": 958.6743719577789,
  "stopped_early": true,
  "status": "completed"
}