{
  "tag": "audit_input_dep_eta0.04_region_audit_B200_seed2",
  "seed": 2,
  "noise_type": "input_dep",
  "eta": 0.04,
  "policy": "region_audit",
  "budget": 200,
  "p": 97,
  "n_train": 5000,
  "hidden": 256,
  "batch_size": 512,
  "epochs_ran": 200000,
  "epochs_planned": 200000,
  "eval_every": 2000,
  "lr": 0.001,
  "weight_decay": 0.02,
  "grok_threshold": 0.95,
  "grok_consecutive": 5,
  "loss_warmup_epochs": 2000,
  "num_corrupted": 200,
  "num_audited": 200,
  "num_corrected": 33,
  "hit_rate": 0.165,
  "correction_rate": 0.165,
  "time_to_grok": null,
  "time_to_0.80": null,
  "time_to_0.90": null,
  "final_test_acc": 0.47242002338186845,
  "final_train_acc": 0.9876,
  "gap_area": 55.88111790838559,
  "auc_test": 42.89648209161441,
  "wall_time_sec": 10670.239195108414,
  "stopped_early": false,
  "status": "completed"
}